sha_mainloop.sv
`default_nettype none
`timescale 1 ns / 10 ps

module sha_mainloop	#(parameter PADDED_SIZE = 512)
					(input logic [PADDED_SIZE-1:0] padded,
					input logic clk, rst,
					output logic [255:0] hashed,
					output logic done);

	function [31:0] K;
		input [6:0] x;
		K = k[2047-x*32 -: 32];
	endfunction

	function automatic [31:0] W;
		input [6:0] x;
		input [6:0] y;
		if(^x === 1'bX) W = 32'h777;
		else W = (x<16) ? padded[((PADDED_SIZE-1-y*512)-x*32) -: 32] : rho1(W(x-2, y)) + W(x-7, y) + rho0(W(x-15, y)) + W(x-16, y);
	endfunction

	function automatic [31:0] rho0;
		input [31:0] x;
		if(^x === 1'bX) rho0 = 32'h888;
		else rho0 = {x[6:0],x[31:7]} ^ {x[17:0],x[31:18]} ^ (x >> 3);
	endfunction

	function automatic [31:0] rho1;
		input [31:0] x;
		if(^x === 1'bX) rho1 = 32'h888;
		else rho1 = {x[16:0],x[31:17]} ^ {x[18:0],x[31:19]} ^ (x >> 10);
	endfunction

	function [31:0] ch;
		input [31:0] x,y,z;
		if(^x === 1'bX) ch = 32'h888;
		else ch = (x & y) ^ (~x & z);
	endfunction

	function [31:0] maj;
		input [31:0] x,y,z;
		if(^x === 1'bX) maj = 32'h888;
		else maj = (x & y) ^ (x & z) ^ (y & z);
	endfunction

	function [31:0] sum0;
		input [31:0] x;
		if(^x === 1'bX) sum0 = 32'h888;
		else sum0 = {x[1:0],x[31:2]} ^ {x[12:0],x[31:13]} ^ {x[21:0],x[31:22]};
	endfunction

	function [31:0] sum1;
		input [31:0] x;
		if(^x === 1'bX) sum1 = 32'h888;
		// else sum1 = (x >> 6) ^ (x >> 11) ^ (x >> 25);
		else sum1 = {x[5:0],x[31:6]} ^ {x[10:0],x[31:11]} ^ {x[24:0],x[31:25]};
	endfunction

	logic [255:0] initial_hashes = {32'h6a09e667, 32'hbb67ae85, 32'h3c6ef372, 32'ha54ff53a, 32'h510e527f, 32'h9b05688c, 32'h1f83d9ab, 32'h5be0cd19};
	
	logic [2047:0] k = {32'h428a2f98, 32'h71374491, 32'hb5c0fbcf, 32'he9b5dba5, 32'h3956c25b, 32'h59f111f1, 32'h923f82a4, 32'hab1c5ed5, 32'hd807aa98, 32'h12835b01, 32'h243185be, 32'h550c7dc3, 32'h72be5d74, 32'h80deb1fe, 32'h9bdc06a7, 32'hc19bf174, 32'he49b69c1, 32'hefbe4786, 32'h0fc19dc6, 32'h240ca1cc, 32'h2de92c6f, 32'h4a7484aa, 32'h5cb0a9dc, 32'h76f988da, 32'h983e5152, 32'ha831c66d, 32'hb00327c8, 32'hbf597fc7, 32'hc6e00bf3, 32'hd5a79147, 32'h06ca6351, 32'h14292967, 32'h27b70a85, 32'h2e1b2138, 32'h4d2c6dfc, 32'h53380d13, 32'h650a7354, 32'h766a0abb, 32'h81c2c92e, 32'h92722c85, 32'ha2bfe8a1, 32'ha81a664b, 32'hc24b8b70, 32'hc76c51a3, 32'hd192e819, 32'hd6990624, 32'hf40e3585, 32'h106aa070, 32'h19a4c116, 32'h1e376c08, 32'h2748774c, 32'h34b0bcb5, 32'h391c0cb3, 32'h4ed8aa4a, 32'h5b9cca4f, 32'h682e6ff3, 32'h748f82ee, 32'h78a5636f, 32'h84c87814, 32'h8cc70208, 32'h90befffa, 32'ha4506ceb, 32'hbef9a3f7, 32'hc67178f2};

	logic [31:0] a, b, c, d, e, f, g, h, t1, t2;
	logic [31:0] h1, h2, h3, h4, h5, h6, h7, h8;

	// genvar i;
	logic [6:0] j;
	logic [6:0] i;

	localparam N = PADDED_SIZE/512; // number of blocks

	// for(i=0; i<N; i=i+1) begin

		logic [31:0] ch_efg, maj_abc, sum0_a, sum1_e, kj, wj;

		always_comb begin
			ch_efg = ch(e,f,g);
			maj_abc = maj(a,b,c);
			sum0_a = sum0(a);
			sum1_e = sum1(e);
			wj = W(j, i);
			kj = K(j);
		end

		always @(negedge clk) begin
			// t1 <= h + sum1(e) + ch(e,f,g) + K(j) + W(j);
			// t2 <= sum0(a) + maj(a,b,c);
			t1 <= (h + sum1_e + ch_efg + kj + wj)%4294967296;
			t2 <= (sum0_a + maj_abc)%4294967296;
		end

		always @(posedge clk or posedge rst) begin
			if(rst) begin
				i 	<= 1'b0;
				j 	<= 1'bX;
				h1 	<= 32'h6a09e667;
				h2 	<= 32'hbb67ae85;
				h3 	<= 32'h3c6ef372;
				h4 	<= 32'ha54ff53a;
				h5 	<= 32'h510e527f;
				h6 	<= 32'h9b05688c;
				h7 	<= 32'h1f83d9ab;
				h8 	<= 32'h5be0cd19;
			end
			else if (^j === 1'bX && ^i !== 1'bX) begin
				a <= h1;
				b <= h2;
				c <= h3;
				d <= h4;
				e <= h5;
				f <= h6;
				g <= h7;
				h <= h8;
				j <= 1'd0;
			end
			else if (j < 64) begin
				h <= g;
				g <= f;
				f <= e;
				e <= (d+t1)%4294967296;
				d <= c;
				c <= b;
				b <= a;
				a <= (t1+t2)%4294967296;
				j <= j+1;
			end
			else if (j == 64) begin
				h1 <= a + h1;
				h2 <= b + h2;
				h3 <= c + h3;
				h4 <= d + h4;
				h5 <= e + h5;
				h6 <= f + h6;
				h7 <= g + h7;
				h8 <= h + h8;
				j <= 1'bX;
				if (i<N-1) i <= i+1;
				else begin
					i <= 1'bX;
					done <= 1'b1;
				end
			end
		end
	// end

	assign hashed = {h1, h2, h3, h4, h5, h6, h7, h8};
endmodule

sha_padder.sv
`define PACK_ARRAY(PK_WIDTH,PK_LEN,PK_SRC,PK_DEST)    genvar pk_idx; generate for (pk_idx=0; pk_idx<(PK_LEN); pk_idx=pk_idx+1) begin; assign PK_DEST[((PK_WIDTH)*pk_idx+((PK_WIDTH)-1)):((PK_WIDTH)*pk_idx)] = PK_SRC[pk_idx][((PK_WIDTH)-1):0]; end; endgenerate
`define UNPACK_ARRAY(PK_WIDTH,PK_LEN,PK_DEST,PK_SRC)  genvar unpk_idx; generate for (unpk_idx=0; unpk_idx<(PK_LEN); unpk_idx=unpk_idx+1) begin; assign PK_DEST[unpk_idx][((PK_WIDTH)-1):0] = PK_SRC[((PK_WIDTH)*unpk_idx+(PK_WIDTH-1)):((PK_WIDTH)*unpk_idx)]; end; endgenerate

module sha_padder	#(parameter MSG_SIZE = 24,		// size of full message
					parameter PADDED_SIZE = 512) 
					(input logic [MSG_SIZE-1:0] message,
					output logic [PADDED_SIZE-1:0] padded);
	
	localparam zero_width = PADDED_SIZE-MSG_SIZE-1-64;
	localparam back_0_width = 64-$bits(MSG_SIZE);
	
	assign padded = {message, 1'b1, {zero_width{1'b0}}, {back_0_width{1'b0}}, MSG_SIZE};
endmodule

sha_256.sv
`default_nettype none
`timescale 1 ns / 10 ps

module sha_256	#(parameter MSG_SIZE = 24,
				parameter PADDED_SIZE = 512)
				(input logic [MSG_SIZE-1:0] message,
				input logic clk, rst,
				output logic [255:0] hashed,
				output logic done);

	logic[PADDED_SIZE-1:0] padded;

	sha_padder #(.MSG_SIZE(MSG_SIZE), .PADDED_SIZE(PADDED_SIZE)) padder (.message(message), .padded(padded));
	sha_mainloop #(.PADDED_SIZE(PADDED_SIZE)) loop (.padded(padded), .hashed(hashed), .clk(clk), .rst(rst), .done(done));
endmodule // sha_256

miner.sv
`default_nettype none
`timescale 1 ns / 10 ps

module miner (input logic [639:0] block,
			input logic clk, rst,
			output logic [255:0] hashed,
			output logic done);
	
	logic [255:0] first_hash;
	logic [255:0] secnd_hash;

	logic second_run_rst;
	logic done_first_hash;
	logic done_secnd_hash;

	sha_256 #(.MSG_SIZE(640), .PADDED_SIZE(1024)) first (.message(block), .hashed(first_hash), .clk(clk), .rst(rst), .done(done_first_hash));
	sha_256 #(.MSG_SIZE(256), .PADDED_SIZE(512)) second (.message(first_hash), .hashed(secnd_hash), .clk(clk), .rst(second_run_rst), .done(done_secnd_hash));

	// always @* second_run_rst <= 1'b0;

	always @(posedge clk) begin
		if (done_first_hash === 1'bX) second_run_rst <= 1'b1;
		else if (done_first_hash == 1'b1) second_run_rst <= 1'b0;
	end

	assign done = done_secnd_hash;
	assign hashed = {secnd_hash[7:0], secnd_hash[15:8], secnd_hash[23:16], secnd_hash[31:24], secnd_hash[39:32], secnd_hash[47:40], secnd_hash[55:48], secnd_hash[63:56], secnd_hash[71:64], secnd_hash[79:72], secnd_hash[87:80], secnd_hash[95:88], secnd_hash[103:96], secnd_hash[111:104], secnd_hash[119:112], secnd_hash[127:120], secnd_hash[135:128], secnd_hash[143:136], secnd_hash[151:144], secnd_hash[159:152], secnd_hash[167:160], secnd_hash[175:168], secnd_hash[183:176], secnd_hash[191:184], secnd_hash[199:192], secnd_hash[207:200], secnd_hash[215:208], secnd_hash[223:216], secnd_hash[231:224], secnd_hash[239:232], secnd_hash[247:240], secnd_hash[255:248]};

endmodule

miner_tb.sv
`default_nettype none
`timescale 1 ns / 10 ps

module miner_tb;
	logic[639:0] message;
	logic [255:0] hashed;
	logic clk, rst, done;

	miner uut (.block(message), .hashed(hashed), .clk(clk), .rst(rst), .done(done));

	initial begin
    	$dumpfile("miner_tb.vcd");
    	$dumpvars;
    	assign message = 640'h0100000000000000000000000000000000000000000000000000000000000000000000003ba3edfd7a7b12b27ac72c3e67768f617fc81bc3888a51323a9fb8aa4b1e5e4a29ab5f49ffff001d1dac2b7c;
    	assign clk = 0;
    	assign rst = 1; #5
    	assign rst = 0;
    	while(done !== 1'b1) begin
    		assign clk = ~clk;
    		#5;
    	end
    	$display("FINISHED miner_tb");
    	$display("Hash: %h", hashed);
    	$finish;
	end
endmodule

miner_tb.vcd
$date
	Mon Feb  5 11:53:37 2018
$end
$version
	Icarus Verilog
$end
$timescale
	10ps
$end
$scope module miner_tb $end
$var wire 256 ! hashed [255:0] $end
$var wire 1 " done $end
$var reg 1 # clk $end
$var reg 640 $ message [639:0] $end
$var reg 1 % rst $end
$scope module uut $end
$var wire 640 & block [639:0] $end
$var wire 1 # clk $end
$var wire 1 " done $end
$var wire 1 % rst $end
$var wire 256 ' secnd_hash [255:0] $end
$var wire 256 ( hashed [255:0] $end
$var wire 256 ) first_hash [255:0] $end
$var wire 1 * done_secnd_hash $end
$var wire 1 + done_first_hash $end
$var reg 1 , second_run_rst $end
$scope module first $end
$var wire 1 # clk $end
$var wire 640 - message [639:0] $end
$var wire 1 % rst $end
$var wire 1024 . padded [1023:0] $end
$var wire 256 / hashed [255:0] $end
$var wire 1 + done $end
$scope module loop $end
$var wire 1 # clk $end
$var wire 1 % rst $end
$var wire 1024 0 padded [1023:0] $end
$var wire 256 1 hashed [255:0] $end
$var reg 32 2 a [31:0] $end
$var reg 32 3 b [31:0] $end
$var reg 32 4 c [31:0] $end
$var reg 32 5 ch_efg [31:0] $end
$var reg 32 6 d [31:0] $end
$var reg 1 + done $end
$var reg 32 7 e [31:0] $end
$var reg 32 8 f [31:0] $end
$var reg 32 9 g [31:0] $end
$var reg 32 : h [31:0] $end
$var reg 32 ; h1 [31:0] $end
$var reg 32 < h2 [31:0] $end
$var reg 32 = h3 [31:0] $end
$var reg 32 > h4 [31:0] $end
$var reg 32 ? h5 [31:0] $end
$var reg 32 @ h6 [31:0] $end
$var reg 32 A h7 [31:0] $end
$var reg 32 B h8 [31:0] $end
$var reg 7 C i [6:0] $end
$var reg 256 D initial_hashes [255:0] $end
$var reg 7 E j [6:0] $end
$var reg 2048 F k [2047:0] $end
$var reg 32 G kj [31:0] $end
$var reg 32 H maj_abc [31:0] $end
$var reg 32 I sum0_a [31:0] $end
$var reg 32 J sum1_e [31:0] $end
$var reg 32 K t1 [31:0] $end
$var reg 32 L t2 [31:0] $end
$var reg 32 M wj [31:0] $end
$scope function K $end
$var reg 32 N K [31:0] $end
$var reg 7 O x [6:0] $end
$upscope $end
$scope function W $end
$upscope $end
$scope function ch $end
$var reg 32 P ch [31:0] $end
$var reg 32 Q x [31:0] $end
$var reg 32 R y [31:0] $end
$var reg 32 S z [31:0] $end
$upscope $end
$scope function maj $end
$var reg 32 T maj [31:0] $end
$var reg 32 U x [31:0] $end
$var reg 32 V y [31:0] $end
$var reg 32 W z [31:0] $end
$upscope $end
$scope function rho0 $end
$upscope $end
$scope function rho1 $end
$upscope $end
$scope function sum0 $end
$var reg 32 X sum0 [31:0] $end
$var reg 32 Y x [31:0] $end
$upscope $end
$scope function sum1 $end
$var reg 32 Z sum1 [31:0] $end
$var reg 32 [ x [31:0] $end
$upscope $end
$upscope $end
$scope module padder $end
$var wire 640 \ message [639:0] $end
$var wire 1024 ] padded [1023:0] $end
$upscope $end
$upscope $end
$scope module second $end
$var wire 1 # clk $end
$var wire 256 ^ message [255:0] $end
$var wire 1 , rst $end
$var wire 512 _ padded [511:0] $end
$var wire 256 ` hashed [255:0] $end
$var wire 1 * done $end
$scope module loop $end
$var wire 1 # clk $end
$var wire 1 , rst $end
$var wire 512 a padded [511:0] $end
$var wire 256 b hashed [255:0] $end
$var reg 32 c a [31:0] $end
$var reg 32 d b [31:0] $end
$var reg 32 e c [31:0] $end
$var reg 32 f ch_efg [31:0] $end
$var reg 32 g d [31:0] $end
$var reg 1 * done $end
$var reg 32 h e [31:0] $end
$var reg 32 i f [31:0] $end
$var reg 32 j g [31:0] $end
$var reg 32 k h [31:0] $end
$var reg 32 l h1 [31:0] $end
$var reg 32 m h2 [31:0] $end
$var reg 32 n h3 [31:0] $end
$var reg 32 o h4 [31:0] $end
$var reg 32 p h5 [31:0] $end
$var reg 32 q h6 [31:0] $end
$var reg 32 r h7 [31:0] $end
$var reg 32 s h8 [31:0] $end
$var reg 7 t i [6:0] $end
$var reg 256 u initial_hashes [255:0] $end
$var reg 7 v j [6:0] $end
$var reg 2048 w k [2047:0] $end
$var reg 32 x kj [31:0] $end
$var reg 32 y maj_abc [31:0] $end
$var reg 32 z sum0_a [31:0] $end
$var reg 32 { sum1_e [31:0] $end
$var reg 32 | t1 [31:0] $end
$var reg 32 } t2 [31:0] $end
$var reg 32 ~ wj [31:0] $end
$scope function K $end
$var reg 32 !" K [31:0] $end
$var reg 7 "" x [6:0] $end
$upscope $end
$scope function W $end
$upscope $end
$scope function ch $end
$var reg 32 #" ch [31:0] $end
$var reg 32 $" x [31:0] $end
$var reg 32 %" y [31:0] $end
$var reg 32 &" z [31:0] $end
$upscope $end
$scope function maj $end
$var reg 32 '" maj [31:0] $end
$var reg 32 (" x [31:0] $end
$var reg 32 )" y [31:0] $end
$var reg 32 *" z [31:0] $end
$upscope $end
$scope function rho0 $end
$upscope $end
$scope function rho1 $end
$upscope $end
$scope function sum0 $end
$var reg 32 +" sum0 [31:0] $end
$var reg 32 ," x [31:0] $end
$upscope $end
$scope function sum1 $end
$var reg 32 -" sum1 [31:0] $end
$var reg 32 ." x [31:0] $end
$upscope $end
$upscope $end
$scope module padder $end
$var wire 256 /" message [255:0] $end
$var wire 512 0" padded [511:0] $end
$upscope $end
$upscope $end
$upscope $end
$upscope $end
$enddefinitions $end
#0
$dumpvars
b1101010000010011110011001100111101110110110011110101110100001010011110001101110111100110111001010100101010011111111010100111010010100010000111001010010011111111001101100000101011010001000110000011111100000111101100110101011010110111110000011001101000110011000000000000000000000000000000000000000000000000000000000000000000000000000000000000000000000000000000000000000000000000000000000000000000000000000000000000000000000000000000000000000000000000000000000000000000000000000000000000000000000000000000100000000 0"
b110101000001001111001100110011110111011011001111010111010000101001111000110111011110011011100101010010101001111111101010011101001010001000011100101001001111111100110110000010101101000100011000001111110000011110110011010101101011011111000001100110100011001 /"
bx ."
bx -"
bx ,"
bx +"
bx *"
bx )"
bx ("
bx '"
bx &"
bx %"
bx $"
bx #"
bx ""
bx !"
bx ~
bx }
bx |
bx {
bx z
bx y
bx x
b1000010100010100010111110011000011100010011011101000100100100011011010111000000111110111100111111101001101101011101101110100101001110010101011011000010010110110101100111110001000100011111000110010010001111111000001010100100101010110001110001011110110101011101100000000111101010101001100000010010100000110101101100000001001001000011000110000101101111100101010100001100011111011100001101110010101111100101110101110100100000001101111010110001111111101001101111011100000001101010011111000001100110111111000101110100111001001001101101101001110000011110111110111110010001111000011000001111110000011001110111000110001001000000110010100001110011000010110111101001001011000110111101001010011101001000010010101010010111001011000010101001110111000111011011111001100010001101101010011000001111100101000101010010101010000011000111000110011011011011000000000011001001111100100010111111010110010111111111000111110001101110000000001011111100111101010110100111100100010100011100000110110010100110001101010001000101000010100100101001011001110010011110110111000010101000010100101110000110110010000100111000010011010010110001101101111111000101001100111000000011010001001101100101000010100111001101010100011101100110101000001010101110111000000111000010110010010010111010010010011100100010110010000101101000101011111111101000101000011010100000011010011001100100101111000010010010111000101101110000110001110110110001010001101000111101000110010010111010000001100111010110100110010000011000100100111101000000111000110101100001010001000001101010101000000111000000011001101001001100000100010110000111100011011101101100000010000010011101001000011101110100110000110100101100001011110010110101001110010001110000001100101100110100111011011000101010100100101001011011100111001100101001001111011010000010111001101111111100110111010010001111100000101110111001111000101001010110001101101111100001001100100001111000000101001000110011000111000000100000100010010000101111101111111111111010101001000101000001101100111010111011111011111001101000111111011111000110011100010111100011110010 w
bx v
b110101000001001111001100110011110111011011001111010111010000101001111000110111011110011011100101010010101001111111101010011101001010001000011100101001001111111100110110000010101101000100011000001111110000011110110011010101101011011111000001100110100011001 u
bx t
bx s
bx r
bx q
bx p
bx o
bx n
bx m
bx l
bx k
bx j
bx i
bx h
bx g
bx f
bx e
bx d
bx c
bx b
b1101010000010011110011001100111101110110110011110101110100001010011110001101110111100110111001010100101010011111111010100111010010100010000111001010010011111111001101100000101011010001000110000011111100000111101100110101011010110111110000011001101000110011000000000000000000000000000000000000000000000000000000000000000000000000000000000000000000000000000000000000000000000000000000000000000000000000000000000000000000000000000000000000000000000000000000000000000000000000000000000000000000000000000000100000000 a
bx `
b1101010000010011110011001100111101110110110011110101110100001010011110001101110111100110111001010100101010011111111010100111010010100010000111001010010011111111001101100000101011010001000110000011111100000111101100110101011010110111110000011001101000110011000000000000000000000000000000000000000000000000000000000000000000000000000000000000000000000000000000000000000000000000000000000000000000000000000000000000000000000000000000000000000000000000000000000000000000000000000000000000000000000000000000100000000 _
b110101000001001111001100110011110111011011001111010111010000101001111000110111011110011011100101010010101001111111101010011101001010001000011100101001001111111100110110000010101101000100011000001111110000011110110011010101101011011111000001100110100011001 ^
b100000000000000000000000000000000000000000000000000000000000000000000000000000000000000000000000000000000000000000000000000000000000000000000000000000000000000000000000000000000000000000000000000000000000000000000000000000000000000000000000000000000000000000000000000000000000000000011101110100011111011011111110101111010011110110001001010110010011110101100011100101100001111100110011101110110100011110110000101111111110010000001101111000011100010001000101001010001001100100011101010011111101110001010101001001011000111100101111001001010001010011010101101011111010010011111111111111111000000000001110100011101101011000010101101111100100000000000000000000000000000000000000000000000000000000000000000000000000000000000000000000000000000000000000000000000000000000000000000000000000000000000000000000000000000000000000000000000000000000000000000000000000000000000000000000000000000000000000000000000000000000000000000000000000000000000000000000000000000000000000000000000000000000000000000000000000000000000001010000000 ]
b100000000000000000000000000000000000000000000000000000000000000000000000000000000000000000000000000000000000000000000000000000000000000000000000000000000000000000000000000000000000000000000000000000000000000000000000000000000000000000000000000000000000000000000000000000000000000000011101110100011111011011111110101111010011110110001001010110010011110101100011100101100001111100110011101110110100011110110000101111111110010000001101111000011100010001000101001010001001100100011101010011111101110001010101001001011000111100101111001001010001010011010101101011111010010011111111111111111000000000001110100011101101011000010101101111100 \
bx [
b100010001000 Z
bx Y
b100010001000 X
bx W
bx V
bx U
b100010001000 T
bx S
bx R
bx Q
b100010001000 P
b0x O
bx N
b11101110111 M
bx L
bx K
b100010001000 J
b100010001000 I
b100010001000 H
bx G
b1000010100010100010111110011000011100010011011101000100100100011011010111000000111110111100111111101001101101011101101110100101001110010101011011000010010110110101100111110001000100011111000110010010001111111000001010100100101010110001110001011110110101011101100000000111101010101001100000010010100000110101101100000001001001000011000110000101101111100101010100001100011111011100001101110010101111100101110101110100100000001101111010110001111111101001101111011100000001101010011111000001100110111111000101110100111001001001101101101001110000011110111110111110010001111000011000001111110000011001110111000110001001000000110010100001110011000010110111101001001011000110111101001010011101001000010010101010010111001011000010101001110111000111011011111001100010001101101010011000001111100101000101010010101010000011000111000110011011011011000000000011001001111100100010111111010110010111111111000111110001101110000000001011111100111101010110100111100100010100011100000110110010100110001101010001000101000010100100101001011001110010011110110111000010101000010100101110000110110010000100111000010011010010110001101101111111000101001100111000000011010001001101100101000010100111001101010100011101100110101000001010101110111000000111000010110010010010111010010010011100100010110010000101101000101011111111101000101000011010100000011010011001100100101111000010010010111000101101110000110001110110110001010001101000111101000110010010111010000001100111010110100110010000011000100100111101000000111000110101100001010001000001101010101000000111000000011001101001001100000100010110000111100011011101101100000010000010011101001000011101110100110000110100101100001011110010110101001110010001110000001100101100110100111011011000101010100100101001011011100111001100101001001111011010000010111001101111111100110111010010001111100000101110111001111000101001010110001101101111100001001100100001111000000101001000110011000111000000100000100010010000101111101111111111111010101001000101000001101100111010111011111011111001101000111111011111000110011100010111100011110010 F
b0x E
b110101000001001111001100110011110111011011001111010111010000101001111000110111011110011011100101010010101001111111101010011101001010001000011100101001001111111100110110000010101101000100011000001111110000011110110011010101101011011111000001100110100011001 D
b0 C
b1011011111000001100110100011001 B
b11111100000111101100110101011 A
b10011011000001010110100010001100 @
b1010001000011100101001001111111 ?
b10100101010011111111010100111010 >
b111100011011101111001101110010 =
b10111011011001111010111010000101 <
b1101010000010011110011001100111 ;
bx :
bx 9
bx 8
bx 7
bx 6
b100010001000 5
bx 4
bx 3
bx 2
b110101000001001111001100110011110111011011001111010111010000101001111000110111011110011011100101010010101001111111101010011101001010001000011100101001001111111100110110000010101101000100011000001111110000011110110011010101101011011111000001100110100011001 1
b100000000000000000000000000000000000000000000000000000000000000000000000000000000000000000000000000000000000000000000000000000000000000000000000000000000000000000000000000000000000000000000000000000000000000000000000000000000000000000000000000000000000000000000000000000000000000000011101110100011111011011111110101111010011110110001001010110010011110101100011100101100001111100110011101110110100011110110000101111111110010000001101111000011100010001000101001010001001100100011101010011111101110001010101001001011000111100101111001001010001010011010101101011111010010011111111111111111000000000001110100011101101011000010101101111100100000000000000000000000000000000000000000000000000000000000000000000000000000000000000000000000000000000000000000000000000000000000000000000000000000000000000000000000000000000000000000000000000000000000000000000000000000000000000000000000000000000000000000000000000000000000000000000000000000000000000000000000000000000000000000000000000000000000000000000000000000000000001010000000 0
b110101000001001111001100110011110111011011001111010111010000101001111000110111011110011011100101010010101001111111101010011101001010001000011100101001001111111100110110000010101101000100011000001111110000011110110011010101101011011111000001100110100011001 /
b100000000000000000000000000000000000000000000000000000000000000000000000000000000000000000000000000000000000000000000000000000000000000000000000000000000000000000000000000000000000000000000000000000000000000000000000000000000000000000000000000000000000000000000000000000000000000000011101110100011111011011111110101111010011110110001001010110010011110101100011100101100001111100110011101110110100011110110000101111111110010000001101111000011100010001000101001010001001100100011101010011111101110001010101001001011000111100101111001001010001010011010101101011111010010011111111111111111000000000001110100011101101011000010101101111100100000000000000000000000000000000000000000000000000000000000000000000000000000000000000000000000000000000000000000000000000000000000000000000000000000000000000000000000000000000000000000000000000000000000000000000000000000000000000000000000000000000000000000000000000000000000000000000000000000000000000000000000000000000000000000000000000000000000000000000000000000000000001010000000 .
b100000000000000000000000000000000000000000000000000000000000000000000000000000000000000000000000000000000000000000000000000000000000000000000000000000000000000000000000000000000000000000000000000000000000000000000000000000000000000000000000000000000000000000000000000000000000000000011101110100011111011011111110101111010011110110001001010110010011110101100011100101100001111100110011101110110100011110110000101111111110010000001101111000011100010001000101001010001001100100011101010011111101110001010101001001011000111100101111001001010001010011010101101011111010010011111111111111111000000000001110100011101101011000010101101111100 -
x,
x+
x*
b110101000001001111001100110011110111011011001111010111010000101001111000110111011110011011100101010010101001111111101010011101001010001000011100101001001111111100110110000010101101000100011000001111110000011110110011010101101011011111000001100110100011001 )
bx (
bx '
b100000000000000000000000000000000000000000000000000000000000000000000000000000000000000000000000000000000000000000000000000000000000000000000000000000000000000000000000000000000000000000000000000000000000000000000000000000000000000000000000000000000000000000000000000000000000000000011101110100011111011011111110101111010011110110001001010110010011110101100011100101100001111100110011101110110100011110110000101111111110010000001101111000011100010001000101001010001001100100011101010011111101110001010101001001011000111100101111001001010001010011010101101011111010010011111111111111111000000000001110100011101101011000010101101111100 &
1%
b100000000000000000000000000000000000000000000000000000000000000000000000000000000000000000000000000000000000000000000000000000000000000000000000000000000000000000000000000000000000000000000000000000000000000000000000000000000000000000000000000000000000000000000000000000000000000000011101110100011111011011111110101111010011110110001001010110010011110101100011100101100001111100110011101110110100011110110000101111111110010000001101111000011100010001000101001010001001100100011101010011111101110001010101001001011000111100101111001001010001010011010101101011111010010011111111111111111000000000001110100011101101011000010101101111100 $
0#
x"
bx !
$end
#500
b1100111001101111000000101101110101011110110011000001100011111100011000110100000000101100110110111111101010010000011100101000100111010111101010100111110100101011100101111001101101110001111001000010110101110011001111011101101100111111001100000100101101010 !
b1100111001101111000000101101110101011110110011000001100011111100011000110100000000101100110110111111101010010000011100101000100111010111101010100111110100101011100101111001101101110001111001000010110101110011001111011101101100111111001100000100101101010 (
b0x ""
b11101110111 ~
b100010001000 {
b100010001000 -"
b100010001000 z
b100010001000 +"
b100010001000 y
b100010001000 '"
b100010001000 f
b100010001000 #"
b1011011111000001100110100011001 s
b11111100000111101100110101011 r
b10011011000001010110100010001100 q
b1010001000011100101001001111111 p
b10100101010011111111010100111010 o
b111100011011101111001101110010 n
b10111011011001111010111010000101 m
b110101000001001111001100110011110111011011001111010111010000101001111000110111011110011011100101010010101001111111101010011101001010001000011100101001001111111100110110000010101101000100011000001111110000011110110011010101101011011111000001100110100011001 '
b110101000001001111001100110011110111011011001111010111010000101001111000110111011110011011100101010010101001111111101010011101001010001000011100101001001111111100110110000010101101000100011000001111110000011110110011010101101011011111000001100110100011001 `
b110101000001001111001100110011110111011011001111010111010000101001111000110111011110011011100101010010101001111111101010011101001010001000011100101001001111111100110110000010101101000100011000001111110000011110110011010101101011011111000001100110100011001 b
b1101010000010011110011001100111 l
b0x v
b0 t
b1000010100010100010111110011000 G
b1000010100010100010111110011000 N
b0 O
b1000000000000000000000000 M
b110101100001110010011100101011 J
b110101100001110010011100101011 Z
b1010001000011100101001001111111 [
b11001110001000001011010001111110 I
b11001110001000001011010001111110 X
b1101010000010011110011001100111 Y
b111010011011111110011001100111 H
b111010011011111110011001100111 T
b1101010000010011110011001100111 U
b10111011011001111010111010000101 V
b111100011011101111001101110010 W
b11111100001011100100110001100 5
b11111100001011100100110001100 P
b1010001000011100101001001111111 Q
b10011011000001010110100010001100 R
b11111100000111101100110101011 S
b0 E
b1011011111000001100110100011001 :
b11111100000111101100110101011 9
b10011011000001010110100010001100 8
b1010001000011100101001001111111 7
b10100101010011111111010100111010 6
b111100011011101111001101110010 4
b10111011011001111010111010000101 3
b1101010000010011110011001100111 2
1,
1#
0%
#1000
b1000100010000 }
b1000100100001001101011100101 L
b11110100011101111110110101101000 K
0#
#1500
b1110001001101110100010010010001 G
b1110001001101110100010010010001 N
b1 O
b0 M
b111101110001010111011000111010 J
b111101110001010111011000111010 Z
b10011001110001111110001010100010 [
b11111000011001111110110100011 I
b11111000011001111110110100011 X
b11111101000010001000100001001101 Y
b11111011000010011010111001000101 H
b11111011000010011010111001000101 T
b11111101000010001000100001001101 U
b1101010000010011110011001100111 V
b10111011011001111010111010000101 W
b10011000001100100101000101110 5
b10011000001100100101000101110 P
b10011001110001111110001010100010 Q
b1010001000011100101001001111111 R
b10011011000001010110100010001100 S
b1 E
b11111101000010001000100001001101 2
b1101010000010011110011001100111 3
b10111011011001111010111010000101 4
b111100011011101111001101110010 6
b10011001110001111110001010100010 7
b1010001000011100101001001111111 8
b10011011000001010110100010001100 9
b11111100000111101100110101011 :
1#
#2000
b11010000101101010101111101000 L
b11100001100001101101111010100100 K
0#
#2500
b10110101110000001111101111001111 G
b10110101110000001111101111001111 N
b10 O
b11100000010111010110001011111100 J
b11100000010111010110001011111100 Z
b11101111101011101001000010110 [
b11100101010101000110110100001 I
b11100101010101000110110100001 X
b11111011100111011000101010001100 Y
b11111011000010011000101001001101 H
b11111011000010011000101001001101 T
b11111011100111011000101010001100 U
b11111101000010001000100001001101 V
b1101010000010011110011001100111 W
b1011001110011111100001001101011 5
b1011001110011111100001001101011 P
b11101111101011101001000010110 Q
b10011001110001111110001010100010 R
b1010001000011100101001001111111 S
b10 E
b11111011100111011000101010001100 2
b11111101000010001000100001001101 3
b1101010000010011110011001100111 4
b10111011011001111010111010000101 6
b11101111101011101001000010110 7
b10011001110001111110001010100010 8
b1010001000011100101001001111111 9
b10011011000001010110100010001100 :
1#
#3000
b10111101101000001011111101110 L
b10001010111100111000100111000010 K
0#
#3500
b11101001101101011101101110100101 G
b11101001101101011101101110100101 N
b11 O
b111000011011011000010000100101 J
b111000011011011000010000100101 Z
b1000110010110110011100001000111 [
b10111011101010100011111111011011 I
b10111011101010100011111111011011 X
b10100010101001111010000110110000 Y
b11111011100011011000100010001100 H
b11111011100011011000100010001100 T
b10100010101001111010000110110000 U
b11111011100111011000101010001100 V
b11111101000010001000100001001101 W
b10011101110101011101001010100110 5
b10011101110101011101001010100110 P
b1000110010110110011100001000111 Q
b11101111101011101001000010110 R
b10011001110001111110001010100010 S
b11 E
b10100010101001111010000110110000 2
b11111011100111011000101010001100 3
b11111101000010001000100001001101 4
b1101010000010011110011001100111 6
b1000110010110110011100001000111 7
b11101111101011101001000010110 8
b10011001110001111110001010100010 9
b1010001000011100101001001111111 :
1#
#4000
b10110111001101111100100001100111 L
b10001000001111000010011101111 K
0#
