sha_mainloop.sv
`default_nettype none
`timescale 1 ns / 10 ps

module sha_mainloop	#(parameter PADDED_SIZE = 512)
					(input logic [PADDED_SIZE-1:0] padded,
					input logic clk, rst);

	function [31:0] K;
		input [6:0] x;
		K = k[2047-x*32 -: 32];
	endfunction

	function automatic [31:0] W;
		input [6:0] x;
		if(^x === 1'bX) W = 32'h777;
		else W = (x<16) ? padded[(511-x*32) -: 32] : rho1(W(x-2)) + W(x-7) + rho0(W(x-15)) + W(x-16);
	endfunction

	function automatic [31:0] rho0;
		input [31:0] x;
		if(^x === 1'bX) rho0 = 32'h888;
		else rho0 = {x[6:0],x[31:7]} ^ {x[17:0],x[31:18]} ^ (x >> 3);
	endfunction

	function automatic [31:0] rho1;
		input [31:0] x;
		if(^x === 1'bX) rho1 = 32'h888;
		else rho1 = {x[16:0],x[31:17]} ^ {x[18:0],x[31:19]} ^ (x >> 10);
	endfunction

	function [31:0] ch;
		input [31:0] x,y,z;
		if(^x === 1'bX) ch = 32'h888;
		else ch = (x & y) ^ (~x & z);
	endfunction

	function [31:0] maj;
		input [31:0] x,y,z;
		if(^x === 1'bX) maj = 32'h888;
		else maj = (x & y) ^ (x & z) ^ (y & z);
	endfunction

	function [31:0] sum0;
		input [31:0] x;
		if(^x === 1'bX) sum0 = 32'h888;
		else sum0 = {x[1:0],x[31:2]} ^ {x[12:0],x[31:13]} ^ {x[21:0],x[31:22]};
	endfunction

	function [31:0] sum1;
		input [31:0] x;
		if(^x === 1'bX) sum1 = 32'h888;
		// else sum1 = (x >> 6) ^ (x >> 11) ^ (x >> 25);
		else sum1 = {x[5:0],x[31:6]} ^ {x[10:0],x[31:11]} ^ {x[24:0],x[31:25]};
	endfunction

	localparam N = PADDED_SIZE/512; // number of blocks

	logic [255:0] initial_hashes = {32'h6a09e667, 32'hbb67ae85, 32'h3c6ef372, 32'ha54ff53a, 32'h510e527f, 32'h9b05688c, 32'h1f83d9ab, 32'h5be0cd19};
	
	logic [2047:0] k = {32'h428a2f98, 32'h71374491, 32'hb5c0fbcf, 32'he9b5dba5, 32'h3956c25b, 32'h59f111f1, 32'h923f82a4, 32'hab1c5ed5, 32'hd807aa98, 32'h12835b01, 32'h243185be, 32'h550c7dc3, 32'h72be5d74, 32'h80deb1fe, 32'h9bdc06a7, 32'hc19bf174, 32'he49b69c1, 32'hefbe4786, 32'h0fc19dc6, 32'h240ca1cc, 32'h2de92c6f, 32'h4a7484aa, 32'h5cb0a9dc, 32'h76f988da, 32'h983e5152, 32'ha831c66d, 32'hb00327c8, 32'hbf597fc7, 32'hc6e00bf3, 32'hd5a79147, 32'h06ca6351, 32'h14292967, 32'h27b70a85, 32'h2e1b2138, 32'h4d2c6dfc, 32'h53380d13, 32'h650a7354, 32'h766a0abb, 32'h81c2c92e, 32'h92722c85, 32'ha2bfe8a1, 32'ha81a664b, 32'hc24b8b70, 32'hc76c51a3, 32'hd192e819, 32'hd6990624, 32'hf40e3585, 32'h106aa070, 32'h19a4c116, 32'h1e376c08, 32'h2748774c, 32'h34b0bcb5, 32'h391c0cb3, 32'h4ed8aa4a, 32'h5b9cca4f, 32'h682e6ff3, 32'h748f82ee, 32'h78a5636f, 32'h84c87814, 32'h8cc70208, 32'h90befffa, 32'ha4506ceb, 32'hbef9a3f7, 32'hc67178f2};

	logic [31:0] a, b, c, d, e, f, g, h, t1, t2;
	logic [31:0] h1, h2, h3, h4, h5, h6, h7, h8;

	genvar i;
	logic [6:0] j;

	for(i=0; i<N; i=i+1) begin

		logic [31:0] ch_efg, maj_abc, sum0_a, sum1_e, kj, wj;

		always_comb begin
			ch_efg = ch(e,f,g);
			maj_abc = maj(a,b,c);
			sum0_a = sum0(a);
			sum1_e = sum1(e);
			wj = W(j);
			kj = K(j);
		end

		always @(negedge clk) begin
			// t1 <= h + sum1(e) + ch(e,f,g) + K(j) + W(j);
			// t2 <= sum0(a) + maj(a,b,c);
			t1 <= (h + sum1_e + ch_efg + kj + wj)%4294967296;
			t2 <= (sum0_a + maj_abc)%4294967296;
		end

		always @(posedge clk or posedge rst) begin
			if(rst) begin
				j 	<= 1'bX;
				h1 	<= 32'h6a09e667;
				h2 	<= 32'hbb67ae85;
				h3 	<= 32'h3c6ef372;
				h4 	<= 32'ha54ff53a;
				h5 	<= 32'h510e527f;
				h6 	<= 32'h9b05688c;
				h7 	<= 32'h1f83d9ab;
				h8 	<= 32'h5be0cd19;
			end
			else if (^j === 1'bX) begin
				a <= h1;
				b <= h2;
				c <= h3;
				d <= h4;
				e <= h5;
				f <= h6;
				g <= h7;
				h <= h8;
				j <= 1'd0;
			end
			else if (j < 64) begin
				h <= g;
				g <= f;
				f <= e;
				e <= (d+t1)%4294967296;
				d <= c;
				c <= b;
				b <= a;
				a <= (t1+t2)%4294967296;
				j <= j+1;
			end
			else if (j == 64) begin
				h1 <= a + h1;
				h2 <= b + h2;
				h3 <= c + h3;
				h4 <= d + h4;
				h5 <= e + h5;
				h6 <= f + h6;
				h7 <= g + h7;
				h8 <= h + h8;
				j <= j+1;
			end
		end
	end
endmodule

sha_mainloop_tb.sv
`default_nettype none
`timescale 1 ns / 10 ps

module sha_mainloop_tb;
	logic [511:0] padded;
	logic clk, rst;

	sha_mainloop uut(.padded(padded), .clk(clk), .rst(rst));

	initial begin
    	$dumpfile("sha_mainloop_tb.vcd");
    	$dumpvars;
    	assign padded = 512'b01100001011000100110001110000000000000000000000000000000000000000000000000000000000000000000000000000000000000000000000000000000000000000000000000000000000000000000000000000000000000000000000000000000000000000000000000000000000000000000000000000000000000000000000000000000000000000000000000000000000000000000000000000000000000000000000000000000000000000000000000000000000000000000000000000000000000000000000000000000000000000000000000000000000000000000000000000000000000000000000000000000000000000000000000011000;
    	assign clk = 0;
    	assign rst = 1;
    	#5;
    	assign clk = 1; #5
    	assign rst = 0; #5
    	for(int i=0; i<150; i++) begin
    		assign clk = ~clk;
    		#5;
    	end
    	$display("FINISHED mainloop_tb");
    	$finish;
	end
endmodule

sha_mainloop_tb.vcd
$date
	Sun Feb  4 16:58:54 2018
$end
$version
	Icarus Verilog
$end
$timescale
	10ps
$end
$scope module sha_mainloop_tb $end
$var reg 1 ! clk $end
$var reg 512 " padded [511:0] $end
$var reg 1 # rst $end
$scope module uut $end
$var wire 1 ! clk $end
$var wire 512 $ padded [511:0] $end
$var wire 1 # rst $end
$var reg 32 % a [31:0] $end
$var reg 32 & b [31:0] $end
$var reg 32 ' c [31:0] $end
$var reg 32 ( d [31:0] $end
$var reg 32 ) e [31:0] $end
$var reg 32 * f [31:0] $end
$var reg 32 + g [31:0] $end
$var reg 32 , h [31:0] $end
$var reg 32 - h1 [31:0] $end
$var reg 32 . h2 [31:0] $end
$var reg 32 / h3 [31:0] $end
$var reg 32 0 h4 [31:0] $end
$var reg 32 1 h5 [31:0] $end
$var reg 32 2 h6 [31:0] $end
$var reg 32 3 h7 [31:0] $end
$var reg 32 4 h8 [31:0] $end
$var reg 256 5 initial_hashes [255:0] $end
$var reg 7 6 j [6:0] $end
$var reg 2048 7 k [2047:0] $end
$var reg 32 8 t1 [31:0] $end
$var reg 32 9 t2 [31:0] $end
$scope function K $end
$var reg 32 : K [31:0] $end
$var reg 7 ; x [6:0] $end
$upscope $end
$scope function W $end
$upscope $end
$scope function ch $end
$var reg 32 < ch [31:0] $end
$var reg 32 = x [31:0] $end
$var reg 32 > y [31:0] $end
$var reg 32 ? z [31:0] $end
$upscope $end
$scope function maj $end
$var reg 32 @ maj [31:0] $end
$var reg 32 A x [31:0] $end
$var reg 32 B y [31:0] $end
$var reg 32 C z [31:0] $end
$upscope $end
$scope function rho0 $end
$upscope $end
$scope function rho1 $end
$upscope $end
$scope function sum0 $end
$var reg 32 D sum0 [31:0] $end
$var reg 32 E x [31:0] $end
$upscope $end
$scope function sum1 $end
$var reg 32 F sum1 [31:0] $end
$var reg 32 G x [31:0] $end
$upscope $end
$scope begin genblk1[0] $end
$var reg 32 H ch_efg [31:0] $end
$var reg 32 I kj [31:0] $end
$var reg 32 J maj_abc [31:0] $end
$var reg 32 K sum0_a [31:0] $end
$var reg 32 L sum1_e [31:0] $end
$var reg 32 M wj [31:0] $end
$upscope $end
$upscope $end
$scope begin $ivl_for_loop0 $end
$var integer 32 N i [31:0] $end
$upscope $end
$upscope $end
$enddefinitions $end
#0
$dumpvars
b0 N
b11101110111 M
b100010001000 L
b100010001000 K
b100010001000 J
bx I
b100010001000 H
bx G
b100010001000 F
bx E
b100010001000 D
bx C
bx B
bx A
b100010001000 @
bx ?
bx >
bx =
b100010001000 <
b0x ;
bx :
bx 9
bx 8
b1000010100010100010111110011000011100010011011101000100100100011011010111000000111110111100111111101001101101011101101110100101001110010101011011000010010110110101100111110001000100011111000110010010001111111000001010100100101010110001110001011110110101011101100000000111101010101001100000010010100000110101101100000001001001000011000110000101101111100101010100001100011111011100001101110010101111100101110101110100100000001101111010110001111111101001101111011100000001101010011111000001100110111111000101110100111001001001101101101001110000011110111110111110010001111000011000001111110000011001110111000110001001000000110010100001110011000010110111101001001011000110111101001010011101001000010010101010010111001011000010101001110111000111011011111001100010001101101010011000001111100101000101010010101010000011000111000110011011011011000000000011001001111100100010111111010110010111111111000111110001101110000000001011111100111101010110100111100100010100011100000110110010100110001101010001000101000010100100101001011001110010011110110111000010101000010100101110000110110010000100111000010011010010110001101101111111000101001100111000000011010001001101100101000010100111001101010100011101100110101000001010101110111000000111000010110010010010111010010010011100100010110010000101101000101011111111101000101000011010100000011010011001100100101111000010010010111000101101110000110001110110110001010001101000111101000110010010111010000001100111010110100110010000011000100100111101000000111000110101100001010001000001101010101000000111000000011001101001001100000100010110000111100011011101101100000010000010011101001000011101110100110000110100101100001011110010110101001110010001110000001100101100110100111011011000101010100100101001011011100111001100101001001111011010000010111001101111111100110111010010001111100000101110111001111000101001010110001101101111100001001100100001111000000101001000110011000111000000100000100010010000101111101111111111111010101001000101000001101100111010111011111011111001101000111111011111000110011100010111100011110010 7
b0x 6
b110101000001001111001100110011110111011011001111010111010000101001111000110111011110011011100101010010101001111111101010011101001010001000011100101001001111111100110110000010101101000100011000001111110000011110110011010101101011011111000001100110100011001 5
b1011011111000001100110100011001 4
b11111100000111101100110101011 3
b10011011000001010110100010001100 2
b1010001000011100101001001111111 1
b10100101010011111111010100111010 0
b111100011011101111001101110010 /
b10111011011001111010111010000101 .
b1101010000010011110011001100111 -
bx ,
bx +
bx *
bx )
bx (
bx '
bx &
bx %
b1100001011000100110001110000000000000000000000000000000000000000000000000000000000000000000000000000000000000000000000000000000000000000000000000000000000000000000000000000000000000000000000000000000000000000000000000000000000000000000000000000000000000000000000000000000000000000000000000000000000000000000000000000000000000000000000000000000000000000000000000000000000000000000000000000000000000000000000000000000000000000000000000000000000000000000000000000000000000000000000000000000000000000000000000011000 $
1#
b1100001011000100110001110000000000000000000000000000000000000000000000000000000000000000000000000000000000000000000000000000000000000000000000000000000000000000000000000000000000000000000000000000000000000000000000000000000000000000000000000000000000000000000000000000000000000000000000000000000000000000000000000000000000000000000000000000000000000000000000000000000000000000000000000000000000000000000000000000000000000000000000000000000000000000000000000000000000000000000000000000000000000000000000000011000 "
0!
$end
#500
1!
#1000
0#
#1500
b1000100010000 9
0!
#2000
b1000010100010100010111110011000 I
b1000010100010100010111110011000 :
b0 ;
b1100001011000100110001110000000 M
b110101100001110010011100101011 L
b110101100001110010011100101011 F
b1010001000011100101001001111111 G
b11001110001000001011010001111110 K
b11001110001000001011010001111110 D
b1101010000010011110011001100111 E
b111010011011111110011001100111 J
b111010011011111110011001100111 @
b1101010000010011110011001100111 A
b10111011011001111010111010000101 B
b111100011011101111001101110010 C
b11111100001011100100110001100 H
b11111100001011100100110001100 <
b1010001000011100101001001111111 =
b10011011000001010110100010001100 >
b11111100000111101100110101011 ?
b0 6
b1011011111000001100110100011001 ,
b11111100000111101100110101011 +
b10011011000001010110100010001100 *
b1010001000011100101001001111111 )
b10100101010011111111010100111010 (
b111100011011101111001101110010 '
b10111011011001111010111010000101 &
b1101010000010011110011001100111 %
1!
b1 N
#2500
b1000100100001001101011100101 9
b1010100110110100101000011101000 8
0!
b10 N
#3000
b1110001001101110100010010010001 I
b1110001001101110100010010010001 :
b1 ;
b0 M
b1011010100101001111110100101101 L
b1011010100101001111110100101101 F
b11111010001010100100011000100010 G
b10100010100111110110010011010001 K
b10100010100111110110010011010001 D
b1011101011010101110101111001101 E
b1111011011010111110111011000101 J
b1111011011010111110111011000101 @
b1011101011010101110101111001101 A
b1101010000010011110011001100111 B
b10111011011001111010111010000101 C
b1010001000011110110101010101110 H
b1010001000011110110101010101110 <
b11111010001010100100011000100010 =
b1010001000011100101001001111111 >
b10011011000001010110100010001100 ?
b1 6
b1011101011010101110101111001101 %
b1101010000010011110011001100111 &
b10111011011001111010111010000101 '
b111100011011101111001101110010 (
b11111010001010100100011000100010 )
b1010001000011100101001001111111 *
b10011011000001010110100010001100 +
b11111100000111101100110101011 ,
1!
b11 N
#3500
b11110000010110101001110010110 9
b111100010111111000011000010111 8
0!
b100 N
#4000
b10110101110000001111101111001111 I
b10110101110000001111101111001111 :
b10 ;
b1110011111100001110010010010101 L
b1110011111100001110010010010101 F
b1111000110011100111100110001001 G
b110000100101101101000001010100 K
b110000100101101101000001010100 D
b1011010011010101101100110101101 E
b1011010011010101110101111101101 J
b1011010011010101110101111101101 @
b1011010011010101101100110101101 A
b1011101011010101110101111001101 B
b1101010000010011110011001100111 C
b1111001000010100100001001110110 H
b1111001000010100100001001110110 <
b1111000110011100111100110001001 =
b11111010001010100100011000100010 >
b1010001000011100101001001111111 ?
b10 6
b1011010011010101101100110101101 %
b1011101011010101110101111001101 &
b1101010000010011110011001100111 '
b10111011011001111010111010000101 (
b1111000110011100111100110001001 )
b11111010001010100100011000100010 *
b1010001000011100101001001111111 +
b10011011000001010110100010001100 ,
1!
b101 N
#4500
b10001011000000011011110001000001 9
b111101110000011000101101100110 8
0!
b110 N
#5000
b11101001101101011101101110100101 I
b11101001101101011101101110100101 :
b11 ;
b110000001110111010000111100 L
b110000001110111010000111100 F
b11111001001010010011100111101011 G
b11000010000100000000100011010000 K
b11000010000100000000100011010000 D
b11001000110000110100011110100111 E
b1011000011010101100101110101101 J
b1011000011010101100101110101101 @
b11001000110000110100011110100111 A
b1011010011010101101100110101101 B
b1011101011010101110101111001101 C
b1111010000010100111111110001001 H
b1111010000010100111111110001001 <
b11111001001010010011100111101011 =
b1111000110011100111100110001001 >
b11111010001010100100011000100010 ?
b11 6
b11001000110000110100011110100111 %
b1011010011010101101100110101101 &
b1011101011010101110101111001101 '
b1101010000010011110011001100111 (
b11111001001010010011100111101011 )
b1111000110011100111100110001001 *
b11111010001010100100011000100010 +
b1010001000011100101001001111111 ,
1!
b111 N
#5500
b11010011110101101010001111101 9
b10111010110101100010000111101001 8
0!
b1000 N
#6000
b111001010101101100001001011011 I
b111001010101101100001001011011 :
b100 ;
b111010100100110011010000110010 L
b111010100100110011010000110010 F
b100100111000000000100001010000 G
b1000101101110110000110001001011 K
b1000101101110110000110001001011 D
b11010101010100001111011001100110 E
b11011000010000101101011110100111 J
b11011000010000101101011110100111 @
b11010101010100001111011001100110 A
b11001000110000110100011110100111 B
b1011010011010101101100110101101 C
b1111000001011100111100111001001 H
b1111000001011100111100111001001 <
b100100111000000000100001010000 =
b11111001001010010011100111101011 >
b1111000110011100111100110001001 ?
b100 6
b11010101010100001111011001100110 %
b11001000110000110100011110100111 &
b1011010011010101101100110101101 '
b1011101011010101110101111001101 (
b100100111000000000100001010000 )
b11111001001010010011100111101011 *
b1111000110011100111100110001001 +
b11111010001010100100011000100010 ,
1!
b1001 N
#6500
b11101111111011110001111110010 9
b11100110010000101011011001111000 8
0!
b1010 N
#7000
b1011001111100010001000111110001 I
b1011001111100010001000111110001 :
b101 ;
b10001011011101111110000110011100 L
b10001011011101111110000110011100 F
b1000011101011011010001001000101 G
b1010000001010011010110010001111 K
b1010000001010011010110010001111 D
b100010000001001101001101010 E
b11000100010000001101011001100110 J
b11000100010000001101011001100110 @
b100010000001001101001101010 A
b11010101010100001111011001100110 B
b11001000110000110100011110100111 C
b10111000101000000001100111101010 H
b10111000101000000001100111101010 <
b1000011101011011010001001000101 =
b100100111000000000100001010000 >
b11111001001010010011100111101011 ?
b101 6
b100010000001001101001101010 %
b11010101010100001111011001100110 &
b11001000110000110100011110100111 '
b1011010011010101101100110101101 (
b1000011101011011010001001000101 )
b100100111000000000100001010000 *
b11111001001010010011100111101011 +
b1111000110011100111100110001001 ,
1!
b1011 N
#7500
b10100011010101000001011110101 9
b10110110101111000011100000000 8
0!
b1100 N
#8000
b10010010001111111000001010100100 I
b10010010001111111000001010100100 :
b110 ;
b1010110110111011101110110 L
b1010110110111011101110110 F
b1110001010000100110000010101101 G
b1101010111100000110011000000 K
b1101010111100000110011000000 D
b101011010000100000100111110101 E
b101010000001001101001100110 J
b101010000001001101001100110 @
b101011010000100000100111110101 A
b100010000001001101001101010 B
b11010101010100001111011001100110 C
b1000101101000000010100001010101 H
b1000101101000000010100001010101 <
b1110001010000100110000010101101 =
b1000011101011011010001001000101 >
b100100111000000000100001010000 ?
b110 6
b101011010000100000100111110101 %
b100010000001001101001101010 &
b11010101010100001111011001100110 '
b11001000110000110100011110100111 (
b1110001010000100110000010101101 )
b1000011101011011010001001000101 *
b100100111000000000100001010000 +
b11111001001010010011100111101011 ,
1!
b1101 N
#8500
b10010100111101010011100100110 9
b11010010011001000101110001011010 8
0!
b1110 N
#9000
b10101011000111000101111011010101 I
b10101011000111000101111011010101 :
b111 ;
b10101100011011111101010101001 L
b10101100011011111101010101001 F
b10011011001001111010010000000001 G
b101001010010011110101101101100 K
b101001010010011110101101101100 D
b11100101000000110000001110000000 E
b100101010000100000101111100000 J
b100101010000100000101111100000 @
b11100101000000110000001110000000 A
b101011010000100000100111110101 B
b100010000001001101001101010 C
b1010001100010100010001001000101 H
b1010001100010100010001001000101 <
b10011011001001111010010000000001 =
b1110001010000100110000010101101 >
b1000011101011011010001001000101 ?
b111 6
b11100101000000110000001110000000 %
b101011010000100000100111110101 &
b100010000001001101001101010 '
b11010101010100001111011001100110 (
b10011011001001111010010000000001 )
b1110001010000100110000010101101 *
b1000011101011011010001001000101 +
b100100111000000000100001010000 ,
1!
b1111 N
#9500
b1001110100010111111011101001100 9
b110111000101001000010000010011 8
0!
b10000 N
#10000
b11011000000001111010101010011000 I
b11011000000001111010101010011000 :
b1000 ;
b10011001101011010010010111000000 L
b10011001101011010010010111000000 F
b1100011001010111101001111001 G
b10111010011110010100110111000010 K
b10111010011110010100110111000010 D
b10000101101000000111101101011111 E
b10100101000000100000101111010101 J
b10100101000000100000101111010101 @
b10000101101000000111101101011111 A
b11100101000000110000001110000000 B
b101011010000100000100111110101 C
b1111001001001110010000010000101 H
b1111001001001110010000010000101 <
b1100011001010111101001111001 =
b10011011001001111010010000000001 >
b1110001010000100110000010101101 ?
b1000 6
b10000101101000000111101101011111 %
b11100101000000110000001110000000 &
b101011010000100000100111110101 '
b100010000001001101001101010 (
b1100011001010111101001111001 )
b10011011001001111010010000000001 *
b1110001010000100110000010101101 +
b1000011101011011010001001000101 ,
1!
b10001 N
#10500
b1011111011110110101100110010111 9
b101110100010011001001100100010 8
0!
b10010 N
#11000
b10010100000110101101100000001 I
b10010100000110101101100000001 :
b1001 ;
b11100100010110111011011111101010 L
b11100100010110111011011111101010 F
b110010110010100010110110001100 G
b10101111111111010110100110001 K
b10101111111111010110100110001 D
b10001110000001001110110010111001 E
b10000101000000000110101110011001 J
b10000101000000000110101110011001 @
b10001110000001001110110010111001 A
b10000101101000000111101101011111 B
b11100101000000110000001110000000 C
b10001001011001011010100000001001 H
b10001001011001011010100000001001 <
b110010110010100010110110001100 =
b1100011001010111101001111001 >
b10011011001001111010010000000001 ?
b1001 6
b10001110000001001110110010111001 %
b10000101101000000111101101011111 &
b11100101000000110000001110000000 '
b101011010000100000100111110101 (
b110010110010100010110110001100 )
b1100011001010111101001111001 *
b10011011001001111010010000000001 +
b1110001010000100110000010101101 ,
1!
b10011 N
#11500
b10011011000000000001100011001010 9
b11110001100001110001101110100001 8
0!
b10100 N
#12000
b100100001100011000010110111110 I
b100100001100011000010110111110 :
b1010 ;
b10001110001000100111011010111100 L
b10001110001000100111011010111100 F
b11100110010010010010110010110 G
b1011100101011000000011100010001 K
b1011100101011000000011100010001 D
b10001100100001110011010001101011 E
b10001100100001000111110001111011 J
b10001100100001000111110001111011 @
b10001100100001110011010001101011 A
b10001110000001001110110010111001 B
b10000101101000000111101101011111 C
b10000111011000111111111101101 H
b10000111011000111111111101101 <
b11100110010010010010110010110 =
b110010110010100010110110001100 >
b1100011001010111101001111001 ?
b1010 6
b10001100100001110011010001101011 %
b10001110000001001110110010111001 &
b10000101101000000111101101011111 '
b11100101000000110000001110000000 (
b11100110010010010010110010110 )
b110010110010100010110110001100 *
b1100011001010111101001111001 +
b10011011001001111010010000000001 ,
1!
b10101 N
#12500
b11101001001100001000001110001100 9
b1011110011010000010000001101000 8
0!
b10110 N
#13000
b1010101000011000111110111000011 I
b1010101000011000111110111000011 :
b1011 ;
b1101001100101000011010111001010 L
b1101001100101000011010111001010 F
b1000011011010110010001111101000 G
b1101100110010111100010100100110 K
b1101100110010111100010100100110 D
b1000111100110001010001111110100 E
b10001110100001001010010011111001 J
b10001110100001001010010011111001 @
b1000111100110001010001111110100 A
b10001100100001110011010001101011 B
b10001110000001001110110010111001 C
b110000110010010010110110000100 H
b110000110010010010110110000100 <
b1000011011010110010001111101000 =
b11100110010010010010110010110 >
b110010110010100010110110001100 ?
b1011 6
b1000111100110001010001111110100 %
b10001100100001110011010001101011 &
b10001110000001001110110010111001 '
b10000101101000000111101101011111 (
b1000011011010110010001111101000 )
b11100110010010010010110010110 *
b110010110010100010110110001100 +
b1100011001010111101001111001 ,
1!
b10111 N
#13500
b11111011010100000110101000011111 9
b11111011110011110101101110001010 8
0!
b11000 N
#14000
b1110010101111100101110101110100 I
b1110010101111100101110101110100 :
b1100 ;
b11001100110111101110011001100001 L
b11001100110111101110011001100001 F
b10000001011011111101011011101001 G
b101111100111101110111001001000 K
b101111100111101110111001001000 D
b11110111000111111100010110101001 E
b11000111100111111010010111101001 J
b11000111100111111010010111101001 @
b11110111000111111100010110101001 A
b1000111100110001010001111110100 B
b10001100100001110011010001101011 C
b11101111010110010001111111110 H
b11101111010110010001111111110 <
b10000001011011111101011011101001 =
b1000011011010110010001111101000 >
b11100110010010010010110010110 ?
b1100 6
b11110111000111111100010110101001 %
b1000111100110001010001111110100 &
b10001100100001110011010001101011 '
b10001110000001001110110010111001 (
b10000001011011111101011011101001 )
b1000011011010110010001111101000 *
b11100110010010010010110010110 +
b110010110010100010110110001100 ,
1!
b11001 N
#14500
b11110111001111101001010000110001 9
b10010000010100101001010101011111 8
0!
b11010 N
#15000
b10000000110111101011000111111110 I
b10000000110111101011000111111110 :
b1101 ;
b1000101110111001100011110111 L
b1000101110111001100011110111 F
b11110010101111000001000011000 G
b101001110001100011010011110011 K
b101001110001100011010011110011 D
b10000111100100010010100110010000 E
b11000111100110011010000110110000 J
b11000111100110011010000110110000 @
b10000111100100010010100110010000 A
b11110111000111111100010110101001 B
b1000111100110001010001111110100 C
b1000001011011111010001111101000 H
b1000001011011111010001111101000 <
b11110010101111000001000011000 =
b10000001011011111101011011101001 >
b1000011011010110010001111101000 ?
b1101 6
b10000111100100010010100110010000 %
b11110111000111111100010110101001 &
b1000111100110001010001111110100 '
b10001100100001110011010001101011 (
b11110010101111000001000011000 )
b10000001011011111101011011101001 *
b1000011011010110010001111101000 +
b11100110010010010010110010110 ,
1!
b11011 N
#15500
b11110001010111111101011010100011 9
b11100111110100110001010001110011 8
0!
b11100 N
#16000
b10011011110111000000011010100111 I
b10011011110111000000011010100111 :
b1110 ;
b1001111001110111000110101010000 L
b1001111001110111000110101010000 F
b1110100010110100100100011011110 G
b100101010101100010100000110110 K
b100101010101100010100000110110 D
b11011001001100101110101100010110 E
b11010111000100111110100110010000 J
b11010111000100111110100110010000 @
b11011001001100101110101100010110 A
b10000111100100010010100110010000 B
b11110111000111111100010110101001 C
b10010101011101111001011000111001 H
b10010101011101111001011000111001 <
b1110100010110100100100011011110 =
b11110010101111000001000011000 >
b10000001011011111101011011101001 ?
b1110 6
b11011001001100101110101100010110 %
b10000111100100010010100110010000 &
b11110111000111111100010110101001 '
b1000111100110001010001111110100 (
b1110100010110100100100011011110 )
b11110010101111000001000011000 *
b10000001011011111101011011101001 +
b1000011011010110010001111101000 ,
1!
b11101 N
#16500
b11111100011010100001000111000110 9
b11000011111110100100111000011000 8
0!
b11110 N
#17000
b11000001100110111111000101110100 I
b11000001100110111111000101110100 :
b1111 ;
b11000 M
b10111000110101100011111110010011 L
b10111000110101100011111110010011 F
b1011100100101111001000001100 G
b11011111100100000110111111010100 K
b11011111100100000110111111010100 D
b11000000011001000101111111011110 E
b11000001001100000110101110010110 J
b11000001001100000110101110010110 @
b11000000011001000101111111011110 A
b11011001001100101110101100010110 B
b10000111100100010010100110010000 C
b10100010101110100000000011100 H
b10100010101110100000000011100 <
b1011100100101111001000001100 =
b1110100010110100100100011011110 >
b11110010101111000001000011000 ?
b1111 6
b11000000011001000101111111011110 %
b11011001001100101110101100010110 &
b10000111100100010010100110010000 '
b11110111000111111100010110101001 (
b1011100100101111001000001100 )
b1110100010110100100100011011110 *
b11110010101111000001000011000 +
b10000001011011111101011011101001 ,
1!
b11111 N
#17500
b10100000110000001101101101101010 9
b10000001110010100100000100100 8
0!
b100000 N
#18000
b11100100100110110110100111000001 I
b11100100100110110110100111000001 :
b10000 ;
b1100001011000100110001110000000 M
b100001001110110110100110010101 L
b100001001110110110100110010101 F
b111010110010000110111001101 G
b1011000110001010011010111110001 K
b1011000110001010011010111110001 D
b10110000111110100010001110001110 E
b11010000011100100110101110011110 J
b11010000011100100110101110011110 @
b10110000111110100010001110001110 A
b11000000011001000101111111011110 B
b11011001001100101110101100010110 C
b1110011000100100100000000011110 H
b1110011000100100100000000011110 <
b111010110010000110111001101 =
b1011100100101111001000001100 >
b1110100010110100100100011011110 ?
b10000 6
b10110000111110100010001110001110 %
b11000000011001000101111111011110 &
b11011001001100101110101100010110 '
b10000111100100010010100110010000 (
b111010110010000110111001101 )
b1011100100101111001000001100 *
b1110100010110100100100011011110 +
b11110010101111000001000011000 ,
1!
b100001 N
#18500
b101001001101111010000110001111 9
b11111000101000101111100100001100 8
0!
b100010 N
#19000
b11101111101111100100011110000110 I
b11101111101111100100011110000110 :
b10001 ;
b11110000000000000000 M
b111011100000011001100001001110 L
b111011100000011001100001001110 F
b10000000001101000010001010011100 G
b1110110110001011100010011110101 K
b1110110110001011100010011110101 D
b100001110110101001101010011011 E
b10100000111110100001101110011110 J
b10100000111110100001101110011110 @
b100001110110101001101010011011 A
b10110000111110100010001110001110 B
b11000000011001000101111111011110 C
b1011100100101101000010001100 H
b1011100100101101000010001100 <
b10000000001101000010001010011100 =
b111010110010000110111001101 >
b1011100100101111001000001100 ?
b10001 6
b100001110110101001101010011011 %
b10110000111110100010001110001110 &
b11000000011001000101111111011110 '
b11011001001100101110101100010110 (
b10000000001101000010001010011100 )
b111010110010000110111001101 *
b1011100100101111001000001100 +
b1110100010110100100100011011110 ,
1!
b100011 N
#19500
b10111101111111110000010010011 9
b10101011001110111111100100111110 8
0!
b100100 N
#20000
b1111110000011001110111000110 I
b1111110000011001110111000110 :
b10010 ;
b1111101101010000110010000000101 M
b11101111111100110001110000001111 L
b11101111111100110001110000001111 F
b10000100011011101110010001010100 G
b1010001010101111010011010100001 K
b1010001010101111010011010100001 D
b11000010111110111101100111010001 E
b10100000111110101001101110011011 J
b10100000111110101001101110011011 @
b11000010111110111101100111010001 A
b100001110110101001101010011011 B
b10110000111110100010001110001110 C
b10000011001101010010100110011101 H
b10000011001101010010100110011101 <
b10000100011011101110010001010100 =
b10000000001101000010001010011100 >
b111010110010000110111001101 ?
b10010 6
b11000010111110111101100111010001 %
b100001110110101001101010011011 &
b10110000111110100010001110001110 '
b11000000011001000101111111011110 (
b10000100011011101110010001010100 )
b10000000001101000010001010011100 *
b111010110010000110111001101 +
b1011100100101111001000001100 ,
1!
b100101 N
#20500
b11110010010100100100001000111100 9
b1100001001010011100110000011 8
0!
b100110 N
#21000
b100100000011001010000111001100 I
b100100000011001010000111001100 :
b10011 ;
b1100000000000000000001111000110 M
b11101111110001110000011110110000 L
b11101111110001110000011110110000 F
b11001100100010011001100101100001 G
b11111111100011001101001010101101 K
b11111111100011001101001010101101 D
b11111110011101110111101110111111 E
b11100010111110111101101110011011 J
b11100010111110111101101110011011 @
b11111110011101110111101110111111 A
b11000010111110111101100111010001 B
b100001110110101001101010011011 C
b10000100001111001010001011011100 H
b10000100001111001010001011011100 <
b11001100100010011001100101100001 =
b10000100011011101110010001010100 >
b10000000001101000010001010011100 ?
b10011 6
b11111110011101110111101110111111 %
b11000010111110111101100111010001 &
b100001110110101001101010011011 '
b10110000111110100010001110001110 (
b11001100100010011001100101100001 )
b10000100011011101110010001010100 *
b10000000001101000010001010011100 +
b111010110010000110111001101 ,
1!
b100111 N
#21500
b11100010100010001010111001001000 9
b11111111011010010101110111101011 8
0!
b101000 N
